{
  "api": [
    {
      "id": 0,
      "gender": "female",
      "firstName": "Vimbiso",
      "lastName": "Bak",
      "email": "vimbiso37@somewhere.dk"
    },
    {
      "id": 1,
      "gender": "male",
      "firstName": "Lance",
      "lastName": "Schrøder",
      "email": "lance47@somewhere.dk"
    },
    {
      "id": 2,
      "gender": "female",
      "firstName": "Humra",
      "lastName": "Fischer",
      "email": "humra70@somewhere.dk"
    },
    {
      "id": 3,
      "gender": "female",
      "firstName": "Adixia",
      "lastName": "Lind",
      "email": "adixia49@somewhere.dk"
    },
    {
      "id": 4,
      "gender": "male",
      "firstName": "Louiie",
      "lastName": "Schultz",
      "email": "louiie9@somewhere.dk"
    },
    {
      "id": 5,
      "gender": "male",
      "firstName": "Inge",
      "lastName": "Juhl",
      "email": "inge16@somewhere.dk"
    },
    {
      "id": 6,
      "gender": "female",
      "firstName": "Selva",
      "lastName": "Riis",
      "email": "selva77@somewhere.dk"
    },
    {
      "id": 7,
      "gender": "female",
      "firstName": "Howa",
      "lastName": "Bendtsen",
      "email": "howa43@somewhere.dk"
    },
    {
      "id": 8,
      "gender": "male",
      "firstName": "Sheraz",
      "lastName": "Laustsen",
      "email": "sheraz93@somewhere.dk"
    },
    {
      "id": 9,
      "gender": "female",
      "firstName": "Lida",
      "lastName": "Kjeldsen",
      "email": "lida91@somewhere.dk"
    },
    {
      "id": 10,
      "gender": "male",
      "firstName": "Siems",
      "lastName": "Nielsen",
      "email": "siems74@somewhere.dk"
    },
    {
      "id": 11,
      "gender": "male",
      "firstName": "Noell",
      "lastName": "Kjærgaard",
      "email": "noell49@somewhere.dk"
    },
    {
      "id": 12,
      "gender": "female",
      "firstName": "Indiya",
      "lastName": "Carstensen",
      "email": "indiya74@somewhere.dk"
    },
    {
      "id": 13,
      "gender": "male",
      "firstName": "Kunuk",
      "lastName": "Jacobsen",
      "email": "kunuk104@somewhere.dk"
    },
    {
      "id": 14,
      "gender": "female",
      "firstName": "Sujeeva",
      "lastName": "Bach",
      "email": "sujeeva88@somewhere.dk"
    },
    {
      "id": 15,
      "gender": "male",
      "firstName": "Thuo",
      "lastName": "Johansson",
      "email": "thuo12@somewhere.dk"
    },
    {
      "id": 16,
      "gender": "female",
      "firstName": "Maryse",
      "lastName": "Bundgaard",
      "email": "maryse15@somewhere.dk"
    },
    {
      "id": 17,
      "gender": "female",
      "firstName": "Poula",
      "lastName": "Toft",
      "email": "poula48@somewhere.dk"
    },
    {
      "id": 18,
      "gender": "male",
      "firstName": "Hervé",
      "lastName": "Lund",
      "email": "hervé69@somewhere.dk"
    },
    {
      "id": 19,
      "gender": "female",
      "firstName": "Kiko",
      "lastName": "Justesen",
      "email": "kiko63@somewhere.dk"
    },
    {
      "id": 20,
      "gender": "female",
      "firstName": "Ulrikkea",
      "lastName": "Juul",
      "email": "ulrikkea19@somewhere.dk"
    },
    {
      "id": 21,
      "gender": "male",
      "firstName": "Stefán",
      "lastName": "Poulsen",
      "email": "stefán46@somewhere.dk"
    },
    {
      "id": 22,
      "gender": "male",
      "firstName": "Alibashi",
      "lastName": "Nygård",
      "email": "alibashi6@somewhere.dk"
    },
    {
      "id": 23,
      "gender": "female",
      "firstName": "Saadet",
      "lastName": "Gregersen",
      "email": "saadet9@somewhere.dk"
    },
    {
      "id": 24,
      "gender": "female",
      "firstName": "Deepika",
      "lastName": "Lind",
      "email": "deepika56@somewhere.dk"
    },
    {
      "id": 25,
      "gender": "female",
      "firstName": "Milione",
      "lastName": "Markussen",
      "email": "milione10@somewhere.dk"
    },
    {
      "id": 26,
      "gender": "female",
      "firstName": "Sacdiya",
      "lastName": "Skovgård",
      "email": "sacdiya9@somewhere.dk"
    },
    {
      "id": 27,
      "gender": "female",
      "firstName": "October",
      "lastName": "Henriksen",
      "email": "october43@somewhere.dk"
    },
    {
      "id": 28,
      "gender": "male",
      "firstName": "Patrekur",
      "lastName": "Thomassen",
      "email": "patrekur13@somewhere.dk"
    },
    {
      "id": 29,
      "gender": "female",
      "firstName": "Yin",
      "lastName": "Bundgård",
      "email": "yin92@somewhere.dk"
    },
    {
      "id": 30,
      "gender": "male",
      "firstName": "Murtadha",
      "lastName": "Dalsgaard",
      "email": "murtadha33@somewhere.dk"
    },
    {
      "id": 31,
      "gender": "female",
      "firstName": "Grâce",
      "lastName": "Vestergård",
      "email": "grâce84@somewhere.dk"
    },
    {
      "id": 32,
      "gender": "female",
      "firstName": "Assie",
      "lastName": "Sloth",
      "email": "assie105@somewhere.dk"
    },
    {
      "id": 33,
      "gender": "female",
      "firstName": "Asil",
      "lastName": "Nørgård",
      "email": "asil44@somewhere.dk"
    },
    {
      "id": 34,
      "gender": "female",
      "firstName": "Carrin",
      "lastName": "Johnsen",
      "email": "carrin82@somewhere.dk"
    },
    {
      "id": 35,
      "gender": "female",
      "firstName": "Luitgard",
      "lastName": "Juul",
      "email": "luitgard84@somewhere.dk"
    },
    {
      "id": 36,
      "gender": "female",
      "firstName": "Wiwi",
      "lastName": "Paulsen",
      "email": "wiwi93@somewhere.dk"
    },
    {
      "id": 37,
      "gender": "male",
      "firstName": "Lars-Bo",
      "lastName": "Dalgård",
      "email": "lars-bo98@somewhere.dk"
    },
    {
      "id": 38,
      "gender": "male",
      "firstName": "Onno",
      "lastName": "Bundgaard",
      "email": "onno30@somewhere.dk"
    },
    {
      "id": 39,
      "gender": "female",
      "firstName": "Yati",
      "lastName": "Bundgaard",
      "email": "yati33@somewhere.dk"
    },
    {
      "id": 40,
      "gender": "male",
      "firstName": "Maher",
      "lastName": "Mogensen",
      "email": "maher78@somewhere.dk"
    },
    {
      "id": 41,
      "gender": "female",
      "firstName": "Rhina",
      "lastName": "Kristoffersen",
      "email": "rhina99@somewhere.dk"
    },
    {
      "id": 42,
      "gender": "male",
      "firstName": "Roy",
      "lastName": "Søgaard",
      "email": "roy45@somewhere.dk"
    },
    {
      "id": 43,
      "gender": "male",
      "firstName": "Theijs",
      "lastName": "Henriksen",
      "email": "theijs61@somewhere.dk"
    },
    {
      "id": 44,
      "gender": "female",
      "firstName": "Isioma",
      "lastName": "Asmussen",
      "email": "isioma52@somewhere.dk"
    },
    {
      "id": 45,
      "gender": "female",
      "firstName": "Tinachafia",
      "lastName": "Nguyen",
      "email": "tinachafia78@somewhere.dk"
    },
    {
      "id": 46,
      "gender": "male",
      "firstName": "Simon-Xander",
      "lastName": "Mølgård",
      "email": "simon-xander90@somewhere.dk"
    },
    {
      "id": 47,
      "gender": "male",
      "firstName": "Esref",
      "lastName": "Paulsen",
      "email": "esref91@somewhere.dk"
    },
    {
      "id": 48,
      "gender": "male",
      "firstName": "Gakuru",
      "lastName": "Mathiesen",
      "email": "gakuru94@somewhere.dk"
    },
    {
      "id": 49,
      "gender": "male",
      "firstName": "Shaho",
      "lastName": "Østergård",
      "email": "shaho71@somewhere.dk"
    },
    {
      "id": 50,
      "gender": "male",
      "firstName": "Villum",
      "lastName": "Schmidt",
      "email": "villum39@somewhere.dk"
    },
    {
      "id": 51,
      "gender": "female",
      "firstName": "Milaani",
      "lastName": "Carstensen",
      "email": "milaani16@somewhere.dk"
    },
    {
      "id": 52,
      "gender": "male",
      "firstName": "Nawras",
      "lastName": "Carstensen",
      "email": "nawras13@somewhere.dk"
    },
    {
      "id": 53,
      "gender": "female",
      "firstName": "Nashmila",
      "lastName": "Bach",
      "email": "nashmila43@somewhere.dk"
    },
    {
      "id": 54,
      "gender": "female",
      "firstName": "Chizaram",
      "lastName": "Munk",
      "email": "chizaram67@somewhere.dk"
    },
    {
      "id": 55,
      "gender": "male",
      "firstName": "Lordswill",
      "lastName": "Davidsen",
      "email": "lordswill105@somewhere.dk"
    },
    {
      "id": 56,
      "gender": "female",
      "firstName": "Isnel",
      "lastName": "Sørensen",
      "email": "isnel78@somewhere.dk"
    },
    {
      "id": 57,
      "gender": "female",
      "firstName": "Inayaah",
      "lastName": "Østergaard",
      "email": "inayaah29@somewhere.dk"
    },
    {
      "id": 58,
      "gender": "female",
      "firstName": "Umalbaninn",
      "lastName": "Lange",
      "email": "umalbaninn79@somewhere.dk"
    },
    {
      "id": 59,
      "gender": "female",
      "firstName": "Gunder",
      "lastName": "Skovgaard",
      "email": "gunder74@somewhere.dk"
    },
    {
      "id": 60,
      "gender": "male",
      "firstName": "Kjenneth",
      "lastName": "Fischer",
      "email": "kjenneth72@somewhere.dk"
    },
    {
      "id": 61,
      "gender": "male",
      "firstName": "Balthezar",
      "lastName": "Poulsen",
      "email": "balthezar48@somewhere.dk"
    },
    {
      "id": 62,
      "gender": "female",
      "firstName": "Olufine",
      "lastName": "Bach",
      "email": "olufine37@somewhere.dk"
    },
    {
      "id": 63,
      "gender": "male",
      "firstName": "Conor",
      "lastName": "Mølgård",
      "email": "conor28@somewhere.dk"
    },
    {
      "id": 64,
      "gender": "female",
      "firstName": "Montie",
      "lastName": "Nissen",
      "email": "montie54@somewhere.dk"
    },
    {
      "id": 65,
      "gender": "male",
      "firstName": "Zhwan",
      "lastName": "Simonsen",
      "email": "zhwan12@somewhere.dk"
    },
    {
      "id": 66,
      "gender": "male",
      "firstName": "Ryad",
      "lastName": "Hougaard",
      "email": "ryad33@somewhere.dk"
    },
    {
      "id": 67,
      "gender": "female",
      "firstName": "Uria",
      "lastName": "Khan",
      "email": "uria56@somewhere.dk"
    },
    {
      "id": 68,
      "gender": "female",
      "firstName": "Hazha",
      "lastName": "Jørgensen",
      "email": "hazha10@somewhere.dk"
    },
    {
      "id": 69,
      "gender": "female",
      "firstName": "Jasaman",
      "lastName": "Jacobsen",
      "email": "jasaman19@somewhere.dk"
    },
    {
      "id": 70,
      "gender": "male",
      "firstName": "Alkhadir",
      "lastName": "Berg",
      "email": "alkhadir59@somewhere.dk"
    },
    {
      "id": 71,
      "gender": "male",
      "firstName": "Freilev",
      "lastName": "Bisgaard",
      "email": "freilev17@somewhere.dk"
    },
    {
      "id": 72,
      "gender": "female",
      "firstName": "Lenra",
      "lastName": "Berg",
      "email": "lenra48@somewhere.dk"
    },
    {
      "id": 73,
      "gender": "female",
      "firstName": "Aija",
      "lastName": "Nissen",
      "email": "aija101@somewhere.dk"
    },
    {
      "id": 74,
      "gender": "female",
      "firstName": "Olivvia",
      "lastName": "Bertelsen",
      "email": "olivvia46@somewhere.dk"
    },
    {
      "id": 75,
      "gender": "male",
      "firstName": "Baraa",
      "lastName": "Koch",
      "email": "baraa72@somewhere.dk"
    },
    {
      "id": 76,
      "gender": "male",
      "firstName": "Isshin",
      "lastName": "Kirkegård",
      "email": "isshin18@somewhere.dk"
    },
    {
      "id": 77,
      "gender": "female",
      "firstName": "Annachristine",
      "lastName": "Khan",
      "email": "annachristine45@somewhere.dk"
    },
    {
      "id": 78,
      "gender": "female",
      "firstName": "Isabele",
      "lastName": "Skovgaard",
      "email": "isabele85@somewhere.dk"
    },
    {
      "id": 79,
      "gender": "male",
      "firstName": "Zelimkhan",
      "lastName": "Skovgaard",
      "email": "zelimkhan14@somewhere.dk"
    },
    {
      "id": 80,
      "gender": "male",
      "firstName": "Cesare",
      "lastName": "Riis",
      "email": "cesare89@somewhere.dk"
    },
    {
      "id": 81,
      "gender": "female",
      "firstName": "Regine",
      "lastName": "Søndergård",
      "email": "regine12@somewhere.dk"
    },
    {
      "id": 82,
      "gender": "male",
      "firstName": "Dagh",
      "lastName": "Christensen",
      "email": "dagh9@somewhere.dk"
    },
    {
      "id": 83,
      "gender": "male",
      "firstName": "Mihal",
      "lastName": "Hougård",
      "email": "mihal82@somewhere.dk"
    },
    {
      "id": 84,
      "gender": "male",
      "firstName": "Bacchus",
      "lastName": "Toft",
      "email": "bacchus78@somewhere.dk"
    },
    {
      "id": 85,
      "gender": "female",
      "firstName": "Micella",
      "lastName": "Ibsen",
      "email": "micella41@somewhere.dk"
    },
    {
      "id": 86,
      "gender": "female",
      "firstName": "Gin",
      "lastName": "Jessen",
      "email": "gin52@somewhere.dk"
    },
    {
      "id": 87,
      "gender": "male",
      "firstName": "Renault",
      "lastName": "Aagård",
      "email": "renault15@somewhere.dk"
    },
    {
      "id": 88,
      "gender": "male",
      "firstName": "Sait",
      "lastName": "Sommer",
      "email": "sait26@somewhere.dk"
    },
    {
      "id": 89,
      "gender": "female",
      "firstName": "Ingerd",
      "lastName": "Jakobsen",
      "email": "ingerd66@somewhere.dk"
    },
    {
      "id": 90,
      "gender": "male",
      "firstName": "Anuson",
      "lastName": "Lund",
      "email": "anuson82@somewhere.dk"
    },
    {
      "id": 91,
      "gender": "female",
      "firstName": "Vaishna",
      "lastName": "Aagaard",
      "email": "vaishna76@somewhere.dk"
    },
    {
      "id": 92,
      "gender": "male",
      "firstName": "Tekin",
      "lastName": "Bjerre",
      "email": "tekin50@somewhere.dk"
    },
    {
      "id": 93,
      "gender": "female",
      "firstName": "Anelle",
      "lastName": "Davidsen",
      "email": "anelle11@somewhere.dk"
    },
    {
      "id": 94,
      "gender": "male",
      "firstName": "Gian",
      "lastName": "Kruse",
      "email": "gian34@somewhere.dk"
    },
    {
      "id": 95,
      "gender": "female",
      "firstName": "Katuzka",
      "lastName": "Mathiasen",
      "email": "katuzka72@somewhere.dk"
    },
    {
      "id": 96,
      "gender": "male",
      "firstName": "Kweku",
      "lastName": "Winther",
      "email": "kweku100@somewhere.dk"
    },
    {
      "id": 97,
      "gender": "female",
      "firstName": "Ausa",
      "lastName": "Andersen",
      "email": "ausa91@somewhere.dk"
    },
    {
      "id": 98,
      "gender": "female",
      "firstName": "Liind",
      "lastName": "Hermansen",
      "email": "liind59@somewhere.dk"
    },
    {
      "id": 99,
      "gender": "female",
      "firstName": "Santhi",
      "lastName": "Jacobsen",
      "email": "santhi34@somewhere.dk"
    },
    {
      "id": 100,
      "gender": "female",
      "firstName": "Fatimeh",
      "lastName": "Jørgensen",
      "email": "fatimeh79@somewhere.dk"
    },
    {
      "id": 101,
      "gender": "female",
      "firstName": "Bebbie",
      "lastName": "Kjær",
      "email": "bebbie16@somewhere.dk"
    },
    {
      "id": 102,
      "gender": "female",
      "firstName": "Sido",
      "lastName": "Olsson",
      "email": "sido20@somewhere.dk"
    },
    {
      "id": 103,
      "gender": "male",
      "firstName": "Trong",
      "lastName": "Pedersen",
      "email": "trong94@somewhere.dk"
    },
    {
      "id": 104,
      "gender": "male",
      "firstName": "Asteway",
      "lastName": "Ahmed",
      "email": "asteway62@somewhere.dk"
    },
    {
      "id": 105,
      "gender": "female",
      "firstName": "Charnell",
      "lastName": "Hedegård",
      "email": "charnell43@somewhere.dk"
    },
    {
      "id": 106,
      "gender": "male",
      "firstName": "Byrial",
      "lastName": "Andresen",
      "email": "byrial73@somewhere.dk"
    },
    {
      "id": 107,
      "gender": "male",
      "firstName": "Zakwan",
      "lastName": "Johannsen",
      "email": "zakwan25@somewhere.dk"
    },
    {
      "id": 108,
      "gender": "female",
      "firstName": "Franciszka",
      "lastName": "Iversen",
      "email": "franciszka29@somewhere.dk"
    },
    {
      "id": 109,
      "gender": "female",
      "firstName": "Yazemin",
      "lastName": "Nielsen",
      "email": "yazemin68@somewhere.dk"
    },
    {
      "id": 110,
      "gender": "male",
      "firstName": "Gen",
      "lastName": "Hald",
      "email": "gen8@somewhere.dk"
    },
    {
      "id": 111,
      "gender": "male",
      "firstName": "Tavs",
      "lastName": "Sommer",
      "email": "tavs58@somewhere.dk"
    },
    {
      "id": 112,
      "gender": "male",
      "firstName": "Kalu",
      "lastName": "Thomassen",
      "email": "kalu27@somewhere.dk"
    },
    {
      "id": 113,
      "gender": "female",
      "firstName": "Vanne",
      "lastName": "Brodersen",
      "email": "vanne40@somewhere.dk"
    },
    {
      "id": 114,
      "gender": "female",
      "firstName": "Victory",
      "lastName": "Jacobsen",
      "email": "victory86@somewhere.dk"
    },
    {
      "id": 115,
      "gender": "female",
      "firstName": "Kirastina",
      "lastName": "Frandsen",
      "email": "kirastina42@somewhere.dk"
    },
    {
      "id": 116,
      "gender": "male",
      "firstName": "Bahadir",
      "lastName": "Møller",
      "email": "bahadir40@somewhere.dk"
    },
    {
      "id": 117,
      "gender": "female",
      "firstName": "Emeliyah",
      "lastName": "Lorentzen",
      "email": "emeliyah34@somewhere.dk"
    },
    {
      "id": 118,
      "gender": "female",
      "firstName": "Annieka",
      "lastName": "Asmussen",
      "email": "annieka90@somewhere.dk"
    },
    {
      "id": 119,
      "gender": "female",
      "firstName": "Isja",
      "lastName": "Koch",
      "email": "isja56@somewhere.dk"
    },
    {
      "id": 120,
      "gender": "female",
      "firstName": "Alekcia",
      "lastName": "Nørgård",
      "email": "alekcia64@somewhere.dk"
    },
    {
      "id": 121,
      "gender": "female",
      "firstName": "Alichia",
      "lastName": "Thorsen",
      "email": "alichia18@somewhere.dk"
    },
    {
      "id": 122,
      "gender": "female",
      "firstName": "Rasha",
      "lastName": "Nielsen",
      "email": "rasha88@somewhere.dk"
    },
    {
      "id": 123,
      "gender": "male",
      "firstName": "Manas",
      "lastName": "Markussen",
      "email": "manas82@somewhere.dk"
    },
    {
      "id": 124,
      "gender": "female",
      "firstName": "Emiliya",
      "lastName": "Jessen",
      "email": "emiliya24@somewhere.dk"
    },
    {
      "id": 125,
      "gender": "female",
      "firstName": "Iggy",
      "lastName": "Hedegaard",
      "email": "iggy31@somewhere.dk"
    },
    {
      "id": 126,
      "gender": "male",
      "firstName": "Rurik",
      "lastName": "Dalgård",
      "email": "rurik66@somewhere.dk"
    },
    {
      "id": 127,
      "gender": "male",
      "firstName": "Epanty",
      "lastName": "Hedegård",
      "email": "epanty50@somewhere.dk"
    },
    {
      "id": 128,
      "gender": "female",
      "firstName": "Linett",
      "lastName": "Laursen",
      "email": "linett79@somewhere.dk"
    },
    {
      "id": 129,
      "gender": "female",
      "firstName": "Jasmitha",
      "lastName": "Winther",
      "email": "jasmitha60@somewhere.dk"
    },
    {
      "id": 130,
      "gender": "male",
      "firstName": "Rinart",
      "lastName": "Knudsen",
      "email": "rinart24@somewhere.dk"
    },
    {
      "id": 131,
      "gender": "male",
      "firstName": "Riber",
      "lastName": "Olsen",
      "email": "riber7@somewhere.dk"
    },
    {
      "id": 132,
      "gender": "male",
      "firstName": "Pagiel",
      "lastName": "Iversen",
      "email": "pagiel101@somewhere.dk"
    },
    {
      "id": 133,
      "gender": "female",
      "firstName": "Safoora",
      "lastName": "Bak",
      "email": "safoora30@somewhere.dk"
    },
    {
      "id": 134,
      "gender": "female",
      "firstName": "Rhema",
      "lastName": "Ahmad",
      "email": "rhema58@somewhere.dk"
    },
    {
      "id": 135,
      "gender": "male",
      "firstName": "Nic",
      "lastName": "Brodersen",
      "email": "nic35@somewhere.dk"
    },
    {
      "id": 136,
      "gender": "female",
      "firstName": "Keneez",
      "lastName": "Hald",
      "email": "keneez91@somewhere.dk"
    },
    {
      "id": 137,
      "gender": "male",
      "firstName": "Gereon",
      "lastName": "Petersen",
      "email": "gereon52@somewhere.dk"
    },
    {
      "id": 138,
      "gender": "male",
      "firstName": "Petur",
      "lastName": "Dalgård",
      "email": "petur76@somewhere.dk"
    },
    {
      "id": 139,
      "gender": "male",
      "firstName": "Errol",
      "lastName": "Winther",
      "email": "errol70@somewhere.dk"
    },
    {
      "id": 140,
      "gender": "female",
      "firstName": "Freja",
      "lastName": "Lindberg",
      "email": "freja54@somewhere.dk"
    },
    {
      "id": 141,
      "gender": "female",
      "firstName": "Ganika",
      "lastName": "Skovgaard",
      "email": "ganika59@somewhere.dk"
    },
    {
      "id": 142,
      "gender": "female",
      "firstName": "Emmanuella",
      "lastName": "Lassen",
      "email": "emmanuella88@somewhere.dk"
    },
    {
      "id": 143,
      "gender": "male",
      "firstName": "Clay",
      "lastName": "Bisgård",
      "email": "clay63@somewhere.dk"
    },
    {
      "id": 144,
      "gender": "female",
      "firstName": "Emaliy",
      "lastName": "Michelsen",
      "email": "emaliy89@somewhere.dk"
    },
    {
      "id": 145,
      "gender": "male",
      "firstName": "Darwich",
      "lastName": "Mikkelsen",
      "email": "darwich77@somewhere.dk"
    },
    {
      "id": 146,
      "gender": "male",
      "firstName": "Ermuunbileg",
      "lastName": "Thygesen",
      "email": "ermuunbileg39@somewhere.dk"
    },
    {
      "id": 147,
      "gender": "female",
      "firstName": "Tawheed",
      "lastName": "Bisgaard",
      "email": "tawheed73@somewhere.dk"
    },
    {
      "id": 148,
      "gender": "male",
      "firstName": "Akhere",
      "lastName": "Klausen",
      "email": "akhere7@somewhere.dk"
    },
    {
      "id": 149,
      "gender": "female",
      "firstName": "Beyzanur",
      "lastName": "Enevoldsen",
      "email": "beyzanur88@somewhere.dk"
    },
    {
      "id": 150,
      "gender": "male",
      "firstName": "Barri",
      "lastName": "Søndergård",
      "email": "barri58@somewhere.dk"
    },
    {
      "id": 151,
      "gender": "female",
      "firstName": "Bedia",
      "lastName": "Hansen",
      "email": "bedia64@somewhere.dk"
    },
    {
      "id": 152,
      "gender": "male",
      "firstName": "António",
      "lastName": "Hald",
      "email": "antónio28@somewhere.dk"
    },
    {
      "id": 153,
      "gender": "male",
      "firstName": "Gösta",
      "lastName": "Buch",
      "email": "gösta40@somewhere.dk"
    },
    {
      "id": 154,
      "gender": "female",
      "firstName": "Jamaad",
      "lastName": "Nygaard",
      "email": "jamaad43@somewhere.dk"
    },
    {
      "id": 155,
      "gender": "male",
      "firstName": "Bjorn",
      "lastName": "Olsen",
      "email": "bjorn80@somewhere.dk"
    },
    {
      "id": 156,
      "gender": "male",
      "firstName": "Yuusuf",
      "lastName": "Dalgård",
      "email": "yuusuf12@somewhere.dk"
    },
    {
      "id": 157,
      "gender": "female",
      "firstName": "Matine",
      "lastName": "Laursen",
      "email": "matine105@somewhere.dk"
    },
    {
      "id": 158,
      "gender": "male",
      "firstName": "Hussien",
      "lastName": "Nygård",
      "email": "hussien21@somewhere.dk"
    },
    {
      "id": 159,
      "gender": "male",
      "firstName": "Harro",
      "lastName": "Mogensen",
      "email": "harro28@somewhere.dk"
    },
    {
      "id": 160,
      "gender": "female",
      "firstName": "Azra",
      "lastName": "Hansen",
      "email": "azra102@somewhere.dk"
    },
    {
      "id": 161,
      "gender": "female",
      "firstName": "Prudence",
      "lastName": "Dam",
      "email": "prudence77@somewhere.dk"
    },
    {
      "id": 162,
      "gender": "female",
      "firstName": "Thais",
      "lastName": "Iversen",
      "email": "thais15@somewhere.dk"
    },
    {
      "id": 163,
      "gender": "female",
      "firstName": "Ilone",
      "lastName": "Pedersen",
      "email": "ilone74@somewhere.dk"
    },
    {
      "id": 164,
      "gender": "male",
      "firstName": "Onno",
      "lastName": "Andersson",
      "email": "onno58@somewhere.dk"
    },
    {
      "id": 165,
      "gender": "male",
      "firstName": "Rasul",
      "lastName": "Bisgaard",
      "email": "rasul35@somewhere.dk"
    },
    {
      "id": 166,
      "gender": "female",
      "firstName": "Shade",
      "lastName": "Buch",
      "email": "shade66@somewhere.dk"
    },
    {
      "id": 167,
      "gender": "male",
      "firstName": "Faour",
      "lastName": "Vinther",
      "email": "faour93@somewhere.dk"
    },
    {
      "id": 168,
      "gender": "female",
      "firstName": "Heza",
      "lastName": "Nørgård",
      "email": "heza23@somewhere.dk"
    },
    {
      "id": 169,
      "gender": "female",
      "firstName": "Cho",
      "lastName": "Bisgaard",
      "email": "cho51@somewhere.dk"
    },
    {
      "id": 170,
      "gender": "female",
      "firstName": "Beatrijs",
      "lastName": "Nguyen",
      "email": "beatrijs90@somewhere.dk"
    },
    {
      "id": 171,
      "gender": "female",
      "firstName": "Sig",
      "lastName": "Dalsgaard",
      "email": "sig58@somewhere.dk"
    },
    {
      "id": 172,
      "gender": "male",
      "firstName": "Suhas",
      "lastName": "Kirkegård",
      "email": "suhas23@somewhere.dk"
    },
    {
      "id": 173,
      "gender": "male",
      "firstName": "Neel",
      "lastName": "Aagård",
      "email": "neel86@somewhere.dk"
    },
    {
      "id": 174,
      "gender": "male",
      "firstName": "Asto",
      "lastName": "Hjorth",
      "email": "asto70@somewhere.dk"
    },
    {
      "id": 175,
      "gender": "male",
      "firstName": "Hawm",
      "lastName": "Holst",
      "email": "hawm34@somewhere.dk"
    },
    {
      "id": 176,
      "gender": "female",
      "firstName": "Mirjeta",
      "lastName": "Johannesen",
      "email": "mirjeta65@somewhere.dk"
    },
    {
      "id": 177,
      "gender": "male",
      "firstName": "Rashmi",
      "lastName": "Persson",
      "email": "rashmi20@somewhere.dk"
    },
    {
      "id": 178,
      "gender": "male",
      "firstName": "Gilbert",
      "lastName": "Bonde",
      "email": "gilbert21@somewhere.dk"
    },
    {
      "id": 179,
      "gender": "male",
      "firstName": "Theobald",
      "lastName": "Søgaard",
      "email": "theobald37@somewhere.dk"
    },
    {
      "id": 180,
      "gender": "male",
      "firstName": "Khan",
      "lastName": "Dalgård",
      "email": "khan61@somewhere.dk"
    },
    {
      "id": 181,
      "gender": "male",
      "firstName": "Lucalaz",
      "lastName": "Gade",
      "email": "lucalaz8@somewhere.dk"
    },
    {
      "id": 182,
      "gender": "male",
      "firstName": "Thyr",
      "lastName": "Mølgård",
      "email": "thyr84@somewhere.dk"
    },
    {
      "id": 183,
      "gender": "male",
      "firstName": "Briand",
      "lastName": "Ahmad",
      "email": "briand89@somewhere.dk"
    },
    {
      "id": 184,
      "gender": "female",
      "firstName": "Kornanong",
      "lastName": "Bisgaard",
      "email": "kornanong83@somewhere.dk"
    },
    {
      "id": 185,
      "gender": "female",
      "firstName": "Judit",
      "lastName": "Johannesen",
      "email": "judit48@somewhere.dk"
    },
    {
      "id": 186,
      "gender": "male",
      "firstName": "Kiami",
      "lastName": "Friis",
      "email": "kiami47@somewhere.dk"
    },
    {
      "id": 187,
      "gender": "male",
      "firstName": "Leonardus",
      "lastName": "Østergaard",
      "email": "leonardus20@somewhere.dk"
    },
    {
      "id": 188,
      "gender": "female",
      "firstName": "Marlena",
      "lastName": "Khan",
      "email": "marlena89@somewhere.dk"
    },
    {
      "id": 189,
      "gender": "male",
      "firstName": "Komail",
      "lastName": "Jessen",
      "email": "komail60@somewhere.dk"
    },
    {
      "id": 190,
      "gender": "male",
      "firstName": "Qarsoq",
      "lastName": "Christoffersen",
      "email": "qarsoq29@somewhere.dk"
    },
    {
      "id": 191,
      "gender": "male",
      "firstName": "Atilio",
      "lastName": "Lindberg",
      "email": "atilio82@somewhere.dk"
    },
    {
      "id": 192,
      "gender": "female",
      "firstName": "Annalina",
      "lastName": "Bundgård",
      "email": "annalina80@somewhere.dk"
    },
    {
      "id": 193,
      "gender": "female",
      "firstName": "Orsolya",
      "lastName": "Vestergård",
      "email": "orsolya18@somewhere.dk"
    },
    {
      "id": 194,
      "gender": "male",
      "firstName": "Myumyun",
      "lastName": "Andreasen",
      "email": "myumyun61@somewhere.dk"
    },
    {
      "id": 195,
      "gender": "male",
      "firstName": "Yves",
      "lastName": "Mølgård",
      "email": "yves62@somewhere.dk"
    },
    {
      "id": 196,
      "gender": "female",
      "firstName": "Nathelie",
      "lastName": "Overgård",
      "email": "nathelie102@somewhere.dk"
    },
    {
      "id": 197,
      "gender": "male",
      "firstName": "Resat",
      "lastName": "Nygård",
      "email": "resat57@somewhere.dk"
    },
    {
      "id": 198,
      "gender": "male",
      "firstName": "Osagie",
      "lastName": "Ahmed",
      "email": "osagie10@somewhere.dk"
    },
    {
      "id": 199,
      "gender": "female",
      "firstName": "Lydi",
      "lastName": "Larsen",
      "email": "lydi19@somewhere.dk"
    }
  ]
}